libanalisis/__init__.py
libanalisis/analisis.py
libanalisis-0.1.2.dist-info/METADATA
libanalisis-0.1.2.dist-info/WHEEL
libanalisis-0.1.2.dist-info/top_level.txt
libanalisis-0.1.2.dist-info/RECORD
