Metadata-Version: 2.1
Name: libanalisis
Version: 0.1.2
Summary: A collection of OpenSeesPy routines for performing several types of analyses
Home-page: https://github.com/odarroyo/libanalisis
Author: Orlando Arroyo
Author-email: odarroyo@uc.cl
License: LICENSE
Requires-Python: >=3.9
Requires-Dist: openseespy >=3.5
Requires-Dist: matplotlib
Requires-Dist: numpy
